mandybrot/__init__.py
mandybrot/colour.py
mandybrot/sample.py
mandybrot-0.0.1.dist-info/METADATA
mandybrot-0.0.1.dist-info/WHEEL
mandybrot-0.0.1.dist-info/RECORD
