Metadata-Version: 2.1
Name: mandybrot
Version: 0.0.1
Summary: Plot the magical Mandelbrot set.
Author: FreddyWordingham
Author-email: freddy@digilab.co.uk
Requires-Python: >=3.8,<4.0
Classifier: Programming Language :: Python :: 3
Classifier: Programming Language :: Python :: 3.8
Classifier: Programming Language :: Python :: 3.9
Classifier: Programming Language :: Python :: 3.10
Classifier: Programming Language :: Python :: 3.11
Requires-Dist: numpy (>=1.24.2,<2.0.0)
Requires-Dist: pillow (>=9.4.0,<10.0.0)
Requires-Dist: tdqm (>=0.0.1,<0.0.2)
